{
  "schema": {
    "name": "projects",
    "version": "1.0.0",
    "fields": [
      { "name": "id", "type": "string", "required": true },
      { "name": "title", "type": "string", "required": true },
      { "name": "status", "type": "string", "required": false },
      { "name": "priority", "type": "string", "required": false },
      { "name": "start_date", "type": "date", "required": false },
      { "name": "end_date", "type": "date", "required": false },
      { "name": "budget", "type": "number", "required": false },
      { "name": "lead", "type": "string", "required": false },
      { "name": "tasks", "type": "json", "required": false },
      { "name": "client", "type": "json", "required": false },
      { "name": "content_items", "type": "json", "required": false },
      { "name": "equipment", "type": "json", "required": false },
      { "name": "sub_projects", "type": "json", "required": false },
      { "name": "content", "type": "json", "required": false },
      { "name": "icon", "type": "string", "required": false },
      { "name": "created_at", "type": "date", "required": false },
      { "name": "updated_at", "type": "date", "required": false },
      { "name": "created_by", "type": "string", "required": false },
      { "name": "last_edited_by", "type": "string", "required": false }
    ]
  },
  "records": [
    { "id": "pj1", "title": "Database System Redesign", "status": "Active", "priority": "High", "start_date": "2026-03-03T00:00:00Z", "end_date": "2026-05-02T00:00:00Z", "budget": 120000, "lead": "Alice", "tasks": ["t1", "t2", "t7"], "client": ["c1"], "content_items": ["ct1", "ct5"], "equipment": ["i1", "i4"], "sub_projects": ["pj6"], "content": [{ "id": "pj1-overview", "type": "heading_2", "content": "Project Overview" }, { "id": "pj1-summary", "type": "paragraph", "content": "Complete redesign of the core database engine with WASM-powered formula evaluation and cross-database relations." }, { "id": "pj1-focus", "type": "bulleted_list", "content": "Showcase populated relations, non-zero rollups, and editable osionos page content from the database row." }], "icon": "🏗️", "created_at": "2026-03-03T00:00:00Z", "updated_at": "2026-04-01T00:00:00Z", "created_by": "Alice", "last_edited_by": "Alice" },
    { "id": "pj2", "title": "Content Marketing Q1", "status": "Active", "priority": "Medium", "start_date": "2026-03-13T00:00:00Z", "end_date": "2026-04-22T00:00:00Z", "budget": 25000, "lead": "Diana", "tasks": ["t4", "t8"], "client": ["c2"], "content_items": ["ct1", "ct2", "ct4", "ct5"], "equipment": [], "sub_projects": [], "icon": "📢", "created_at": "2026-03-13T00:00:00Z", "updated_at": "2026-03-30T00:00:00Z", "created_by": "Diana", "last_edited_by": "Diana" },
    { "id": "pj3", "title": "Infrastructure Upgrade", "status": "Planning", "priority": "High", "start_date": "2026-04-07T00:00:00Z", "end_date": "2026-05-17T00:00:00Z", "budget": 80000, "lead": "Bob", "tasks": ["t5", "t6"], "client": ["c5"], "content_items": [], "equipment": ["i2"], "sub_projects": [], "icon": "🔧", "created_at": "2026-03-28T00:00:00Z", "updated_at": "2026-04-01T00:00:00Z", "created_by": "Bob", "last_edited_by": "Bob" },
    { "id": "pj4", "title": "Client Onboarding Portal", "status": "Completed", "priority": "Medium", "start_date": "2026-02-01T00:00:00Z", "end_date": "2026-03-23T00:00:00Z", "budget": 35000, "lead": "Charlie", "tasks": ["t1", "t3", "t8"], "client": ["c3"], "content_items": ["ct3"], "equipment": ["i3"], "sub_projects": [], "icon": "✅", "created_at": "2026-02-01T00:00:00Z", "updated_at": "2026-03-23T00:00:00Z", "created_by": "Charlie", "last_edited_by": "Charlie" },
    { "id": "pj5", "title": "Mobile App MVP", "status": "On Hold", "priority": "Urgent", "start_date": "2026-03-18T00:00:00Z", "end_date": "2026-06-01T00:00:00Z", "budget": 200000, "lead": "Eve", "tasks": ["t3", "t4"], "client": ["c6"], "content_items": ["ct2"], "equipment": ["i1", "i5"], "sub_projects": [], "icon": "📱", "created_at": "2026-03-18T00:00:00Z", "updated_at": "2026-03-31T00:00:00Z", "created_by": "Eve", "last_edited_by": "Eve" },
    { "id": "pj6", "title": "Analytics Dashboard", "status": "Active", "priority": "High", "start_date": "2026-03-23T00:00:00Z", "end_date": "2026-04-22T00:00:00Z", "budget": 45000, "lead": "Alice", "tasks": ["t2", "t7"], "client": ["c1"], "content_items": ["ct4"], "equipment": ["i4"], "sub_projects": [], "icon": "📊", "created_at": "2026-03-23T00:00:00Z", "updated_at": "2026-04-02T00:00:00Z", "created_by": "Alice", "last_edited_by": "Alice" },
    { "id": "pj7", "title": "Legacy Migration (Cancelled)", "status": "Cancelled", "priority": "Low", "start_date": "2026-01-02T00:00:00Z", "end_date": "2026-02-01T00:00:00Z", "budget": 10000, "lead": "Bob", "tasks": [], "client": ["c4"], "content_items": [], "equipment": [], "sub_projects": [], "icon": "🚫", "created_at": "2026-01-02T00:00:00Z", "updated_at": "2026-02-01T00:00:00Z", "created_by": "Bob", "last_edited_by": "Bob" },
    { "id": "pj8", "title": "R&D Exploration", "status": "Planning", "priority": "Low", "start_date": "2026-04-12T00:00:00Z", "end_date": "2026-07-01T00:00:00Z", "budget": 15000, "lead": "Diana", "tasks": ["t6"], "client": [], "content_items": ["ct3"], "equipment": ["i2", "i3", "i5"], "sub_projects": [], "icon": "🧪", "created_at": "2026-03-31T00:00:00Z", "updated_at": "2026-04-01T00:00:00Z", "created_by": "Diana", "last_edited_by": "Diana" }
  ]
}
